flagit/__init__.py
flagit/flagit.py
flagit/settings.py
flagit-0.3.dist-info/AUTHORS.rst
flagit-0.3.dist-info/LICENSE.txt
flagit-0.3.dist-info/METADATA
flagit-0.3.dist-info/WHEEL
flagit-0.3.dist-info/top_level.txt
flagit-0.3.dist-info/RECORD
