Metadata-Version: 2.2
Name: flagit
Version: 0.3
Summary: ISMN quality control procedures for in situ soil moisture time series
Home-page: https://github.com/TUW-GEO/flagit
Author: TU Wien
Author-email: remote.sensing@geo.tuwien.ac.at
License: mit
Project-URL: Documentation, https://pyscaffold.org/
Platform: any
Classifier: Development Status :: 4 - Beta
Classifier: Programming Language :: Python
Requires-Python: >=3.6
License-File: LICENSE.txt
License-File: AUTHORS.rst
Requires-Dist: setuptools
Requires-Dist: numpy
Requires-Dist: scipy
Requires-Dist: pandas
Provides-Extra: testing
Requires-Dist: pytest; extra == "testing"
Requires-Dist: pytest-cov; extra == "testing"
